MANIFEST.in
README.txt
setup.cfg
setup.py
plonetheme/.DS_Store
plonetheme/__init__.py
plonetheme.hamnavoe.egg-info/PKG-INFO
plonetheme.hamnavoe.egg-info/SOURCES.txt
plonetheme.hamnavoe.egg-info/dependency_links.txt
plonetheme.hamnavoe.egg-info/entry_points.txt
plonetheme.hamnavoe.egg-info/namespace_packages.txt
plonetheme.hamnavoe.egg-info/not-zip-safe
plonetheme.hamnavoe.egg-info/paster_plugins.txt
plonetheme.hamnavoe.egg-info/requires.txt
plonetheme.hamnavoe.egg-info/top_level.txt
plonetheme/hamnavoe/.DS_Store
plonetheme/hamnavoe/__init__.py
plonetheme/hamnavoe/configure.zcml
plonetheme/hamnavoe/profiles.zcml
plonetheme/hamnavoe/setuphandlers.py
plonetheme/hamnavoe/skins.zcml
plonetheme/hamnavoe/tests.py
plonetheme/hamnavoe/version.txt
plonetheme/hamnavoe/browser/__init__.py
plonetheme/hamnavoe/browser/configure.zcml
plonetheme/hamnavoe/browser/hmve.py
plonetheme/hamnavoe/browser/interfaces.py
plonetheme/hamnavoe/browser/splash-image.pt
plonetheme/hamnavoe/browser/splashimage.py
plonetheme/hamnavoe/browser/strapline.pt
plonetheme/hamnavoe/browser/viewlet.pt
plonetheme/hamnavoe/browser/viewlets.py
plonetheme/hamnavoe/browser/images/README.txt
plonetheme/hamnavoe/browser/stylesheets/README.txt
plonetheme/hamnavoe/browser/stylesheets/main.css
plonetheme/hamnavoe/profiles/.DS_Store
plonetheme/hamnavoe/profiles/default/cssregistry.xml
plonetheme/hamnavoe/profiles/default/import_steps.xml
plonetheme/hamnavoe/profiles/default/jsregistry.xml
plonetheme/hamnavoe/profiles/default/metadata.xml
plonetheme/hamnavoe/profiles/default/plonetheme.hamnavoe_various.txt
plonetheme/hamnavoe/profiles/default/skins.xml
plonetheme/hamnavoe/profiles/default/viewlets.xml
plonetheme/hamnavoe/skins/.DS_Store
plonetheme/hamnavoe/skins/plonetheme_hamnavoe_custom_images/CONTENT.txt
plonetheme/hamnavoe/skins/plonetheme_hamnavoe_custom_images/banner.jpg
plonetheme/hamnavoe/skins/plonetheme_hamnavoe_custom_images/bg.gif
plonetheme/hamnavoe/skins/plonetheme_hamnavoe_custom_images/bg.png
plonetheme/hamnavoe/skins/plonetheme_hamnavoe_custom_images/lightfade.png
plonetheme/hamnavoe/skins/plonetheme_hamnavoe_custom_templates/CONTENT.txt
plonetheme/hamnavoe/skins/plonetheme_hamnavoe_custom_templates/main_template.pt
plonetheme/hamnavoe/skins/plonetheme_hamnavoe_styles/CONTENT.txt
plonetheme/hamnavoe/skins/plonetheme_hamnavoe_styles/IEFixes.css.dtml
